polymer/Polymer.py
polymer/__init__.py
polymer/__main__.py
polymer/abc_task.py
polymer-1.0.3.dist-info/METADATA
polymer-1.0.3.dist-info/LICENSE
polymer-1.0.3.dist-info/WHEEL
polymer-1.0.3.dist-info/RECORD
